starmatch/Params.py
starmatch/__init__.py
starmatch/astroalign.py
starmatch/classes.py
starmatch/orientation.py
starmatch/plot.py
starmatch/preprocessing.py
starmatch/distortion/__init__.py
starmatch/distortion/distortion_model.py
starmatch-1.0.1.dist-info/licenses/LICENSE
starmatch-1.0.1.dist-info/METADATA
starmatch-1.0.1.dist-info/WHEEL
starmatch-1.0.1.dist-info/top_level.txt
starmatch-1.0.1.dist-info/RECORD
