Metadata-Version: 2.4
Name: starmatch
Version: 1.0.1
Summary: A package to handle the Star chart matching and astrometric positioning
Home-page: https://github.com/lcx366/STARMATCH
Author: Chunxiao Li
Author-email: lcx366@126.com
License: MIT
Keywords: Star Map Matching,Astrometric positioning,Distortion Calibration,Astronomical Correction
Classifier: Development Status :: 4 - Beta
Classifier: Intended Audience :: Education
Classifier: Intended Audience :: Science/Research
Classifier: Programming Language :: Python :: 3.11
Classifier: Programming Language :: Python :: 3.12
Classifier: Programming Language :: Python :: 3.13
Classifier: License :: OSI Approved :: MIT License
Requires-Python: >=3.10
License-File: LICENSE
Requires-Dist: numpy
Requires-Dist: scipy
Requires-Dist: matplotlib
Requires-Dist: scikit-image
Requires-Dist: astropy
Requires-Dist: GPy
Requires-Dist: statsmodels
Requires-Dist: loess
Requires-Dist: starcatalogquery
Dynamic: author
Dynamic: author-email
Dynamic: classifier
Dynamic: description
Dynamic: description-content-type
Dynamic: home-page
Dynamic: keywords
Dynamic: license
Dynamic: license-file
Dynamic: requires-dist
Dynamic: requires-python
Dynamic: summary
